keanu/__init__.py
keanu/batch.py
keanu/cli.py
keanu/config.py
keanu/data_store.py
keanu/db.py
keanu/db_destination.py
keanu/db_source.py
keanu/py_loader.py
keanu/py_transform.py
keanu/run_statement.py
keanu/sql_loader.py
keanu/sql_transform.py
keanu/test.py
keanu/tracing.py
keanu/transform.py
keanu/util.py
keanu/helpers/__init__.py
keanu/helpers/last_sync.py
keanu/helpers/last_sync.sql
keanu_etl-0.16.5.dist-info/METADATA
keanu_etl-0.16.5.dist-info/WHEEL
keanu_etl-0.16.5.dist-info/entry_points.txt
keanu_etl-0.16.5.dist-info/top_level.txt
keanu_etl-0.16.5.dist-info/RECORD
