Metadata-Version: 2.4
Name: keanu-etl
Version: 0.16.5
Summary: ETL runner
Author-email: Marcin Koziej <marcin@wemove.eu>
Requires-Python: >=3.8
Requires-Dist: click
Requires-Dist: click-aliases
Requires-Dist: pygments
Requires-Dist: pymysql
Requires-Dist: sentry-sdk
Requires-Dist: sqlalchemy==1.4.*
Requires-Dist: PyYAML<=5.3.1
Requires-Dist: pytz
Requires-Dist: cryptography; python_version >= "3.13"
